[
    {
        "Product Name": "Samsung Galaxy A15, Android Smartphone, Dual SIM Mobile Phone, 8GB RAM, 256GB Storage, Light Blue, 1 Year Warranty/Local Version",
        "Price": 889900.0,
        "Rating": "4.1 out of 5 stars",
        "Number of Reviews": "3,197",
        "Image URL": "https://m.media-amazon.com/images/I/51Cida8RecL.__AC_SX300_SY300_QL70_ML2_.jpg",
        "Selected Color": "Light Blue",
        "Brand Name": "SAMSUNG",
        "Operating System": "Android 13.0",
        "RAM Memory Installed": "8 GB",
        "CPU Model": "Snapdragon",
        "CPU Speed": "2.3 GHz",
        "Memory Storage Capacity": "256 GB",
        "Screen Size": "6.5 Inches",
        "Resolution": "1080 x 2340",
        "Refresh Rate": "90 Hz",
        "Model Name": "Galaxy-A15"
    },
    {
        "Product Name": "Samsung Galaxy A55 5G, Android Smartphone, Dual SIM Mobile Phone, 8GB RAM, 128GB Storage, Awesome Navy -1 Year Warranty/Local Version",
        "Price": 2019900.0,
        "Rating": "4.1 out of 5 stars",
        "Number of Reviews": "889",
        "Image URL": "https://m.media-amazon.com/images/I/61ERH+yIyiL._AC_SX300_SY300_.jpg",
        "Selected Color": "Awesome Navy",
        "Brand Name": "SAMSUNG",
        "Operating System": "Android 11.0",
        "RAM Memory Installed": "8 GB",
        "CPU Model": "Snapdragon",
        "CPU Speed": "2.3 GHz",
        "Memory Storage Capacity": "128 GB",
        "Screen Size": "6.5",
        "Resolution": "1080 x 2340",
        "Refresh Rate": "120 Hz",
        "Model Name": "Samsung Galaxy A55"
    },
    {
        "Product Name": "Samsung Galaxy A16 LTE, Android Smartphone, Dual SIM Mobile Phone, 8GB RAM, 256GB Storage, Gray (1 Year Local Warranty)",
        "Price": 959900.0,
        "Rating": "3.6 out of 5 stars",
        "Number of Reviews": "10",
        "Image URL": "https://m.media-amazon.com/images/I/61lzvL4tAqL.__AC_SX300_SY300_QL70_ML2_.jpg",
        "Selected Color": "Gray",
        "Brand Name": "SAMSUNG",
        "Operating System": "Android",
        "RAM Memory Installed": "8 GB",
        "CPU Model": "256 GB",
        "CPU Speed": "1080 x 2340",
        "Memory Storage Capacity": "90 Hz",
        "Screen Size": "Galaxy-A16",
        "Resolution": "Unlocked for All Carriers",
        "Refresh Rate": "LTE",
        "Model Name": "4G"
    },
    {
        "Product Name": "Samsung Galaxy A05s, Android Smartphone, Dual SIM Mobile Phone, 4GB RAM, 64GB Storage, Silver- 1 Year Warranty/Local Version",
        "Price": 539900.0,
        "Rating": "4.1 out of 5 stars",
        "Number of Reviews": "1,118",
        "Image URL": "https://m.media-amazon.com/images/I/61BDP4KDY3L.__AC_SX300_SY300_QL70_ML2_.jpg",
        "Selected Color": "Silver",
        "Brand Name": "SAMSUNG",
        "Operating System": "Android 13.0",
        "RAM Memory Installed": "4 GB",
        "CPU Model": "Snapdragon",
        "CPU Speed": "1.9 GHz",
        "Memory Storage Capacity": "64 GB",
        "Screen Size": "6.7 Inches",
        "Resolution": "1080 x 2400",
        "Refresh Rate": "90 Hz",
        "Model Name": "SM-A057FZSDMEA"
    },
    {
        "Product Name": "Samsung Galaxy A06 Dual Sim 6GB RAM 128GB Storage Android Smartphone, 6.7-Inch Screen Size, Black- 1 Year Warranty/Local Version",
        "Price": 629900.0,
        "Rating": "3.5 out of 5 stars",
        "Number of Reviews": "5",
        "Image URL": "https://m.media-amazon.com/images/I/71OVNSFWVLL.__AC_SX300_SY300_QL70_ML2_.jpg",
        "Selected Color": "Black",
        "Brand Name": "SAMSUNG",
        "Operating System": "Android 14",
        "RAM Memory Installed": "6 GB",
        "CPU Model": "A-Series",
        "CPU Speed": "2 GHz",
        "Memory Storage Capacity": "128 GB",
        "Screen Size": "6.7 Inches",
        "Resolution": "720 x 1600",
        "Refresh Rate": "60 Hz",
        "Model Name": "Galaxy A06"
    },
    {
        "Product Name": "Samsung Galaxy A35 5G, Android Smartphone, Dual SIM Mobile Phone, 8GB RAM, 128GB Storage, Awesome Iceblue, 1 Year Warranty/Local Version",
        "Price": 1655000.0,
        "Rating": "4.2 out of 5 stars",
        "Number of Reviews": "235",
        "Image URL": "https://m.media-amazon.com/images/I/61Wp5qhgwzL.__AC_SY300_SX300_QL70_ML2_.jpg",
        "Selected Color": "Ice Blue",
        "Brand Name": "SAMSUNG",
        "Operating System": "Android",
        "RAM Memory Installed": "8 GB",
        "CPU Model": "A-Series",
        "CPU Speed": "128 GB",
        "Memory Storage Capacity": "6.7",
        "Screen Size": "1080 x 2400",
        "Resolution": "120 Hz",
        "Refresh Rate": "Galaxy-A35 5G",
        "Model Name": "Unlocked for All Carriers"
    },
    {
        "Product Name": "Samsung Galaxy S24 FE, AI Phone, Android Smartphone, 8GB RAM, 256GB Storage, 50MP Camera, Long Battery Life, Large Screen, Graphite - 1 Year Warranty/Local Version",
        "Price": 3950000.0,
        "Rating": "3.8 out of 5 stars",
        "Number of Reviews": "7",
        "Image URL": "https://m.media-amazon.com/images/I/612GsfjWvaL.__AC_SX300_SY300_QL70_ML2_.jpg",
        "Selected Color": null,
        "Brand Name": "SAMSUNG",
        "Operating System": "Android",
        "RAM Memory Installed": "8 GB",
        "CPU Model": "1.2GHz Cortex A9 Processor",
        "CPU Speed": "3.1 GHz",
        "Memory Storage Capacity": "256 GB",
        "Screen Size": "120 Hz",
        "Resolution": "Galaxy S24 FE",
        "Refresh Rate": "Unlocked for All Carriers",
        "Model Name": "5G"
    },
    {
        "Product Name": "SAMSUNG Galaxy S24 Ultra, AI Android Smartphone, 256GB Storage, 12GB RAM, 200MP Camera, S Pen, Long Battery Life, Titanium Gray",
        "Price": 6600000.0,
        "Rating": "4.5 out of 5 stars",
        "Number of Reviews": "3",
        "Image URL": "https://m.media-amazon.com/images/I/713icYPjIZL.__AC_SY300_SX300_QL70_ML2_.jpg",
        "Selected Color": null,
        "Brand Name": "SAMSUNG",
        "Operating System": "Android",
        "RAM Memory Installed": "12 GB",
        "CPU Model": "Snapdragon",
        "CPU Speed": "256 GB",
        "Memory Storage Capacity": "6.8 Inches",
        "Screen Size": "120",
        "Resolution": "Galaxy S24 Ultra",
        "Refresh Rate": "5G",
        "Model Name": "Wi-Fi"
    },
    {
        "Product Name": "Samsung Galaxy S24 FE, AI Phone, Android Smartphone, 8GB RAM, 256GB Storage, 50MP Camera, Long Battery Life, Gray- 1 Year Warranty/Local Version",
        "Price": 3950000.0,
        "Rating": "4.0 out of 5 stars",
        "Number of Reviews": "1,647",
        "Image URL": "https://m.media-amazon.com/images/I/61Yv1htH-KL.__AC_SX300_SY300_QL70_ML2_.jpg",
        "Selected Color": "Gray",
        "Brand Name": "SAMSUNG",
        "Operating System": "Android",
        "RAM Memory Installed": "8 GB",
        "CPU Model": "1.2GHz Cortex A9 Processor",
        "CPU Speed": "256 GB",
        "Memory Storage Capacity": "6.7 Inches",
        "Screen Size": "120 Hz",
        "Resolution": "Galaxy S24 FE",
        "Refresh Rate": "Unlocked for All Carriers",
        "Model Name": "5G"
    },
    {
        "Product Name": "Samsung Galaxy A25, Android Smartphone, Dual SIM Mobile Phone, 8GB RAM, 256GB Storage, Blue Black, 1 Year Warranty/Local Version",
        "Price": 1984859.0909090908,
        "Rating": "3.9 out of 5 stars",
        "Number of Reviews": "145",
        "Image URL": "https://m.media-amazon.com/images/I/61n8R-QRkUL.__AC_SY300_SX300_QL70_ML2_.jpg",
        "Selected Color": "Blue Black",
        "Brand Name": "SAMSUNG",
        "Operating System": "Android 11.0",
        "RAM Memory Installed": "8 GB",
        "CPU Model": "Snapdragon",
        "CPU Speed": "2 GHz",
        "Memory Storage Capacity": "256 GB",
        "Screen Size": "6.5 Inches",
        "Resolution": "1080 x 2340",
        "Refresh Rate": "90 Hz",
        "Model Name": "Galaxy A25 5G"
    },
    {
        "Product Name": "Samsung Galaxy A05 LTE, Android Smartphone, Dual SIM Mobile Phone, 4GB RAM, 128GB Storage,Silver- 1 Year Warranty/Local Version",
        "Price": 599900.0,
        "Rating": "3.9 out of 5 stars",
        "Number of Reviews": "156",
        "Image URL": "https://m.media-amazon.com/images/I/71-QzvIZnVL.__AC_SY300_SX300_QL70_ML2_.jpg",
        "Selected Color": "Silver",
        "Brand Name": "SAMSUNG",
        "Operating System": "Android 10.0",
        "RAM Memory Installed": "4 GB",
        "CPU Model": "Snapdragon",
        "CPU Speed": "1.8 GHz",
        "Memory Storage Capacity": "128 GB",
        "Screen Size": "6.7 Inches",
        "Resolution": "720 x 1600",
        "Refresh Rate": "60 Hz",
        "Model Name": "Samsung Galaxy A05"
    },
    {
        "Product Name": "Samsung Galaxy A05 LTE, Android Smartphone, Dual SIM Mobile Phone, 4GB RAM, 128GB Storage, Light Green- 1 Year Warranty/Local Version",
        "Price": 599900.0,
        "Rating": "4.0 out of 5 stars",
        "Number of Reviews": "225",
        "Image URL": "https://m.media-amazon.com/images/I/71ve-OMxzyL.__AC_SY300_SX300_QL70_ML2_.jpg",
        "Selected Color": "Light Green",
        "Brand Name": "SAMSUNG",
        "Operating System": "Android 10.0",
        "RAM Memory Installed": "4 GB",
        "CPU Model": "MediaTek Helio",
        "CPU Speed": "2 GHz",
        "Memory Storage Capacity": "128 GB",
        "Screen Size": "6.5 Inches",
        "Resolution": "720 x 1600",
        "Refresh Rate": "60 Hz",
        "Model Name": "Samsung Galaxy A05"
    },
    {
        "Product Name": "Samsung Galaxy Z Fold6 (AI Phone) - 12GB RAM + 256GB Storage - Navy, 1 Year Local Warranty",
        "Price": 8450000.0,
        "Rating": "3.2 out of 5 stars",
        "Number of Reviews": "17",
        "Image URL": "https://m.media-amazon.com/images/I/71bFylJeQOL.__AC_SX300_SY300_QL70_ML2_.jpg",
        "Selected Color": "Navy",
        "Brand Name": "SAMSUNG",
        "Operating System": "Android",
        "RAM Memory Installed": "12 GB",
        "CPU Model": "Snapdragon",
        "CPU Speed": "256 GB",
        "Memory Storage Capacity": "7.6",
        "Screen Size": "2560 x 1600",
        "Resolution": "120 Hz",
        "Refresh Rate": "Galaxy Z Fold6",
        "Model Name": "Unlocked for All Carriers"
    },
    {
        "Product Name": "Samsung Galaxy A23 Dual Sim,128 GB, 4GB Ram - Peach",
        "Price": 1984859.0909090908,
        "Rating": "4.3 out of 5 stars",
        "Number of Reviews": "45",
        "Image URL": "https://m.media-amazon.com/images/I/81HwkqsPaIL.__AC_SY300_SX300_QL70_ML2_.jpg",
        "Selected Color": "Peach",
        "Brand Name": "SAMSUNG",
        "Operating System": "Android 10.0",
        "RAM Memory Installed": "4 GB",
        "CPU Model": "Snapdragon",
        "CPU Speed": "1.8 GHz",
        "Memory Storage Capacity": "4 GB",
        "Screen Size": "6.6 Inches",
        "Resolution": "1080 x 2408",
        "Refresh Rate": "90 Hz",
        "Model Name": "Galaxy-A23"
    },
    {
        "Product Name": "Samsung Galaxy A16 LTE, Android Smartphone, Dual SIM Mobile Phone, 4GB RAM, 128GB Storage, Black (1 Year Local Warranty)",
        "Price": 726500.0,
        "Rating": "4.4 out of 5 stars",
        "Number of Reviews": "6",
        "Image URL": "https://m.media-amazon.com/images/I/61Lp1UcxeLL.__AC_SX300_SY300_QL70_ML2_.jpg",
        "Selected Color": null,
        "Brand Name": "SAMSUNG",
        "Operating System": "Android",
        "RAM Memory Installed": "1.2GHz Cortex A8 Processor",
        "CPU Model": "128 GB",
        "CPU Speed": "6.7 Inches",
        "Memory Storage Capacity": "1560 x 720",
        "Screen Size": "Galaxy-A16",
        "Resolution": "Unlocked for All Carriers",
        "Refresh Rate": "LTE",
        "Model Name": "4G"
    },
    {
        "Product Name": "Samsung Galaxy A54 - Dual SIM Mobile Phone Android, 8GB RAM, 256GB, 5G, Awesome White - 1 year Warranty",
        "Price": 1984859.0909090908,
        "Rating": "4.1 out of 5 stars",
        "Number of Reviews": "152",
        "Image URL": "https://m.media-amazon.com/images/I/71b60-HHxjL.__AC_SX300_SY300_QL70_ML2_.jpg",
        "Selected Color": "white",
        "Brand Name": "SAMSUNG",
        "Operating System": "Android 10.0",
        "RAM Memory Installed": "8 GB",
        "CPU Model": "Snapdragon",
        "CPU Speed": "2.4 GHz",
        "Memory Storage Capacity": "256 GB",
        "Screen Size": "54 Inches",
        "Resolution": "1080 x 2400",
        "Refresh Rate": "260 Hz",
        "Model Name": "Samsung Galaxy A54"
    },
    {
        "Product Name": "Samsung Galaxy A25 5G, 6GB RAM, 128GB Storage, Black-1 Year Warranty/Local Version",
        "Price": 1984859.0909090908,
        "Rating": "4.1 out of 5 stars",
        "Number of Reviews": "124",
        "Image URL": "https://m.media-amazon.com/images/I/61n8R-QRkUL.__AC_SY300_SX300_QL70_ML2_.jpg",
        "Selected Color": "Black",
        "Brand Name": "SAMSUNG",
        "Operating System": "Android 11.0",
        "RAM Memory Installed": "6 GB",
        "CPU Model": "Snapdragon",
        "CPU Speed": "128 GB",
        "Memory Storage Capacity": "6.5 Inches",
        "Screen Size": "1080 x 2340",
        "Resolution": "120 Hz",
        "Refresh Rate": "Samsung Galaxy A25 5G",
        "Model Name": "etisalat"
    },
    {
        "Product Name": "SAMSUNG Galaxy S24 Ultra, AI Android Smartphone, 256GB Storage, 12GB RAM, 200MP Camera, S Pen, Long Battery Life, Titanium Black",
        "Price": 1984859.0909090908,
        "Rating": "4.0 out of 5 stars",
        "Number of Reviews": "1",
        "Image URL": "https://m.media-amazon.com/images/I/719HV2e6-sL.__AC_SY300_SX300_QL70_ML2_.jpg",
        "Selected Color": null,
        "Brand Name": "SAMSUNG",
        "Operating System": "Android",
        "RAM Memory Installed": "12 GB",
        "CPU Model": "Snapdragon",
        "CPU Speed": "256 GB",
        "Memory Storage Capacity": "6.8 Inches",
        "Screen Size": "120",
        "Resolution": "Galaxy S24 Ultra",
        "Refresh Rate": "5G",
        "Model Name": "Wi-Fi"
    },
    {
        "Product Name": "Samsung A04S 3GB Ram, 32GB - Black",
        "Price": 1984859.0909090908,
        "Rating": "4.1 out of 5 stars",
        "Number of Reviews": "50",
        "Image URL": "https://m.media-amazon.com/images/I/51P4huodC+L._AC_SY300_SX300_.jpg",
        "Selected Color": "Black",
        "Brand Name": "SAMSUNG",
        "Operating System": "Android 10.0",
        "RAM Memory Installed": "3 GB",
        "CPU Model": "Snapdragon",
        "CPU Speed": "1.8 GHz",
        "Memory Storage Capacity": "32 GB",
        "Screen Size": "Samsung A04S",
        "Resolution": "Bluetooth, Wi-Fi",
        "Refresh Rate": "Black",
        "Model Name": "Wi-Fi"
    },
    {
        "Product Name": "Samsung Galaxy A34 Dual SIM 8GB Ram+128GB ROM (6.5 Inches) (4G) - (Awesome Graphite)",
        "Price": 1984859.0909090908,
        "Rating": "4.3 out of 5 stars",
        "Number of Reviews": "208",
        "Image URL": "https://m.media-amazon.com/images/I/71RqyKk2eBL.__AC_SX300_SY300_QL70_ML2_.jpg",
        "Selected Color": null,
        "Brand Name": "SAMSUNG",
        "Operating System": "Android 13.0",
        "RAM Memory Installed": "8 GB",
        "CPU Model": "Snapdragon",
        "CPU Speed": "1.8 GHz",
        "Memory Storage Capacity": "128 GB",
        "Screen Size": "6.6 Inches",
        "Resolution": "1080 x 2400",
        "Refresh Rate": "120 Hz",
        "Model Name": "Samsung Galaxy A34"
    },
    {
        "Product Name": "Samsung galaxy a34 dual sim mobile phone android, 8gb ram, 128gb, awesome lime - 1 year Warranty",
        "Price": 1475000.0,
        "Rating": "4.2 out of 5 stars",
        "Number of Reviews": "105",
        "Image URL": "https://m.media-amazon.com/images/I/71NvEbrOUFL.__AC_SX300_SY300_QL70_ML2_.jpg",
        "Selected Color": null,
        "Brand Name": "SAMSUNG",
        "Operating System": "Android 13.0",
        "RAM Memory Installed": "8 GB",
        "CPU Model": "Snapdragon",
        "CPU Speed": "1.8 GHz",
        "Memory Storage Capacity": "128 GB",
        "Screen Size": "6.6 Inches",
        "Resolution": "1080 x 2400",
        "Refresh Rate": "144 Hz",
        "Model Name": "Samsung Galaxy A34"
    },
    {
        "Product Name": "Samsung galaxy a34 dual sim mobile phone android, 8gb ram, 128gb, awesome silver",
        "Price": 1475000.0,
        "Rating": "4.1 out of 5 stars",
        "Number of Reviews": "159",
        "Image URL": "https://m.media-amazon.com/images/I/71mHgTssjAL.__AC_SX300_SY300_QL70_ML2_.jpg",
        "Selected Color": null,
        "Brand Name": "SAMSUNG",
        "Operating System": "Android 10.0",
        "RAM Memory Installed": "8 GB",
        "CPU Model": "Snapdragon",
        "CPU Speed": "1.8 GHz",
        "Memory Storage Capacity": "128 GB",
        "Screen Size": "6.6 Inches",
        "Resolution": "1080 x 2400",
        "Refresh Rate": "120 Hz",
        "Model Name": "Samsung Galaxy A34"
    },
    {
        "Product Name": "Samsung Galaxy Z Fold5 Android Smartphone, 12GB RAM, 256GB ROM, Phantom Black - 1 Year Warranty",
        "Price": 1984859.0909090908,
        "Rating": "4.5 out of 5 stars",
        "Number of Reviews": "48",
        "Image URL": "https://m.media-amazon.com/images/I/7102NAlM6FL.__AC_SX300_SY300_QL70_ML2_.jpg",
        "Selected Color": "Phantom Black",
        "Brand Name": "SAMSUNG",
        "Operating System": "Android 13.0",
        "RAM Memory Installed": "12 GB",
        "CPU Model": "Snapdragon",
        "CPU Speed": "2.8 GHz",
        "Memory Storage Capacity": "256 GB",
        "Screen Size": "7.6 Inches",
        "Resolution": "1812 x 2176",
        "Refresh Rate": "70 Hz",
        "Model Name": "Samsung Galaxy Z Fold 5"
    },
    {
        "Product Name": "Samsung Galaxy Z Fold5 Folding Phone, Android Smartphone, 12GB RAM, 512GB Storage, Extended Battery Life, High Resolution Camera, Phantom Black (UAE Version)",
        "Price": 1984859.0909090908,
        "Rating": "4.1 out of 5 stars",
        "Number of Reviews": "13",
        "Image URL": "https://m.media-amazon.com/images/I/7102NAlM6FL.__AC_SX300_SY300_QL70_ML2_.jpg",
        "Selected Color": null,
        "Brand Name": "SAMSUNG",
        "Operating System": "Android 10.0",
        "RAM Memory Installed": "12 GB",
        "CPU Model": "Snapdragon",
        "CPU Speed": "1.8 GHz",
        "Memory Storage Capacity": "512 GB",
        "Screen Size": "7.6 Inches",
        "Resolution": "1812 x 2176",
        "Refresh Rate": "120 Hz",
        "Model Name": "Galaxy Z Fold5"
    },
    {
        "Product Name": "Samsung Galaxy S24 FE, AI Phone, Android Smartphone, Blue, 8GB RAM, 256GB Storage, 50MP Camera and Samsung Galaxy Buds3, Silver, Wireless Bluetooth Earbuds",
        "Price": 4560000.0,
        "Rating": null,
        "Number of Reviews": null,
        "Image URL": "https://m.media-amazon.com/images/I/716ABOx9VyL.__AC_SY300_SX300_QL70_ML2_.jpg",
        "Selected Color": null,
        "Brand Name": "SAMSUNG",
        "Operating System": "Silver",
        "RAM Memory Installed": "In Ear",
        "CPU Model": "In Ear",
        "CPU Speed": "Active Noise Cancellation",
        "Memory Storage Capacity": "3.5 mm Jack",
        "Screen Size": "Galaxy Buds3",
        "Resolution": "Wireless",
        "Refresh Rate": "Bluetooth",
        "Model Name": "Galaxy Buds3"
    },
    {
        "Product Name": "Samsung Galaxy A06 Dual Sim 6GB RAM 128GB Storage Android Smartphone, 6.7-Inch Screen Size, Light Blue and Samsung Galaxy Buds FE, Wireless, with Charging Case, ANC and Sound Customization, Graphite",
        "Price": 888800.0,
        "Rating": null,
        "Number of Reviews": null,
        "Image URL": "https://m.media-amazon.com/images/I/616qwBqjayL.__AC_SY300_SX300_QL70_ML2_.jpg",
        "Selected Color": null,
        "Brand Name": "SAMSUNG",
        "Operating System": "android",
        "RAM Memory Installed": "6 GB",
        "CPU Model": "2 GHz",
        "CPU Speed": "128 GB",
        "Memory Storage Capacity": "6.7 Inches",
        "Screen Size": "720 x 1600",
        "Resolution": "Samsung Galaxy A06",
        "Refresh Rate": "4G",
        "Model Name": "Light Blue"
    },
    {
        "Product Name": "Samsung Galaxy A06 Dual Sim 6GB RAM 128GB Storage Android Smartphone, 6.7-Inch Screen Size, Black and Samsung Galaxy Buds FE, Wireless, with Charging Case, ANC and Sound Customization, Graphite",
        "Price": 888800.0,
        "Rating": null,
        "Number of Reviews": null,
        "Image URL": "https://m.media-amazon.com/images/I/71uf2aP1PAL.__AC_SY300_SX300_QL70_ML2_.jpg",
        "Selected Color": null,
        "Brand Name": "SAMSUNG",
        "Operating System": "android",
        "RAM Memory Installed": "6 GB",
        "CPU Model": "2 GHz",
        "CPU Speed": "128 GB",
        "Memory Storage Capacity": "6.7 Inches",
        "Screen Size": "720 x 1600",
        "Resolution": "Samsung Galaxy A06",
        "Refresh Rate": "4G",
        "Model Name": "Black"
    },
    {
        "Product Name": "Samsung Galaxy A06 Dual Sim 6GB RAM 128GB Storage Android Smartphone, 6.7-Inch Screen Size, Gold and Samsung Galaxy Buds FE, Wireless, with Charging Case, ANC and Sound Customization, Graphite",
        "Price": 888800.0,
        "Rating": null,
        "Number of Reviews": null,
        "Image URL": "https://m.media-amazon.com/images/I/61h-RWYYqEL.__AC_SY300_SX300_QL70_ML2_.jpg",
        "Selected Color": null,
        "Brand Name": "SAMSUNG",
        "Operating System": "android",
        "RAM Memory Installed": "6 GB",
        "CPU Model": "2 GHz",
        "CPU Speed": "128 GB",
        "Memory Storage Capacity": "6.7 Inches",
        "Screen Size": "720 x 1600",
        "Resolution": "Samsung Galaxy A06",
        "Refresh Rate": "4G",
        "Model Name": "Gold"
    },
    {
        "Product Name": "Xiaomi Redmi A3, 3GB RAM | 64GB ROM, 6.71 Inches HD+ 90HZ Display, 5000mAH Battery, 2 SIM, Dual Camera, (4G) Black | 1 year Local warranty",
        "Price": 399900.0,
        "Rating": "3.6 out of 5 stars",
        "Number of Reviews": "168",
        "Image URL": "https://m.media-amazon.com/images/I/7153ZxbAtdL.__AC_SX300_SY300_QL70_ML2_.jpg",
        "Selected Color": "Black",
        "Brand Name": "Xiaomi",
        "Operating System": "Android 10.0",
        "RAM Memory Installed": "Snapdragon",
        "CPU Model": "64 GB",
        "CPU Speed": "6.71 Inches",
        "Memory Storage Capacity": "Redmi A3",
        "Screen Size": "Unlocked for All Carriers",
        "Resolution": "4G",
        "Refresh Rate": "USB",
        "Model Name": "Black"
    },
    {
        "Product Name": "Redmi 13 Midnight Black 8GB RAM 128GB ROM Mediatek helio G91 ultra processor| 6.79\" FHD+ 90Hz display | Triple Camera 108MP + 2MP, 13MP Front camera | 2-pin charger | 18 month manufacturer warranty",
        "Price": 719900.0,
        "Rating": "4.3 out of 5 stars",
        "Number of Reviews": "29",
        "Image URL": "https://m.media-amazon.com/images/I/41usfc8n76L.__AC_SX300_SY300_QL70_ML2_.jpg",
        "Selected Color": "Black",
        "Brand Name": "Xiaomi",
        "Operating System": "Android 14, HyperOS",
        "RAM Memory Installed": "8 GB",
        "CPU Model": "Snapdragon",
        "CPU Speed": "128 GB",
        "Memory Storage Capacity": "6.67 Inches",
        "Screen Size": "1080 x 2460 pixels",
        "Resolution": "90 Hz",
        "Refresh Rate": "Redmi 13",
        "Model Name": "Unlocked for All Carriers"
    },
    {
        "Product Name": "Xiaomi POCO C75 C3NP Immersive 6.88\" display Massive 5160mAh (typ) battery Clear 50MP AI dual camera Powerful octa-core processor Up to 120Hz High refresh rate T\u00dcV Rheinland 8+256 (Black)",
        "Price": 666600.0,
        "Rating": "4.1 out of 5 stars",
        "Number of Reviews": "12",
        "Image URL": "https://m.media-amazon.com/images/I/41A+QSOgIFL._AC_SY300_SX300_.jpg",
        "Selected Color": "Black",
        "Brand Name": "Xiaomi",
        "Operating System": "Android 13.0",
        "RAM Memory Installed": "256 GB",
        "CPU Model": "6.88 Inches",
        "CPU Speed": "1080 x 2460",
        "Memory Storage Capacity": "120 Hz",
        "Screen Size": "POCO C75",
        "Resolution": "1&1",
        "Refresh Rate": "4G",
        "Model Name": "4G"
    },
    {
        "Product Name": "Xiaomi Redmi Note 13 Dual SIM Smartphone 8GB RAM | 128GB ROM (6.67 Inches) (4G) - (Midnight Black) | 1 year Local warranty",
        "Price": 822200.0,
        "Rating": "3.9 out of 5 stars",
        "Number of Reviews": "143",
        "Image URL": "https://m.media-amazon.com/images/I/51xTkm8N0fL.__AC_SX300_SY300_QL70_ML2_.jpg",
        "Selected Color": "Midnight Black",
        "Brand Name": "Xiaomi",
        "Operating System": "MIUI 14",
        "RAM Memory Installed": "8 GB",
        "CPU Model": "Snapdragon",
        "CPU Speed": "1.8 GHz",
        "Memory Storage Capacity": "128 GB",
        "Screen Size": "6.67 Inches",
        "Resolution": "2400 x 1080",
        "Refresh Rate": "120 Hz",
        "Model Name": "Redmi Note 13"
    },
    {
        "Product Name": "Xiaomi Redmi Note 13 (Ice Blue 8GB RAM, 256 Storage) - Super-clear 108MP triple camera |120Hz FHD+AMOLED display | Immersive viewing with ultra-thin bezels | Secure in-screen fingerprint sensor",
        "Price": 990000.0,
        "Rating": "3.9 out of 5 stars",
        "Number of Reviews": "470",
        "Image URL": "https://m.media-amazon.com/images/I/51JupNQ+TrL._AC_SY300_SX300_.jpg",
        "Selected Color": "Blue",
        "Brand Name": "Xiaomi",
        "Operating System": "Android 13.0",
        "RAM Memory Installed": "8 GB",
        "CPU Model": "Snapdragon",
        "CPU Speed": "256 GB",
        "Memory Storage Capacity": "6.67 Inches",
        "Screen Size": "1080 x 2400",
        "Resolution": "120 Hz",
        "Refresh Rate": "Redmi Note 13",
        "Model Name": "3"
    },
    {
        "Product Name": "Xiaomi Redmi Note 12 Dual SIM Smartphone with 4GB RAM, 128GB ROM, 6.67-Inch Display, 4G LTE Connectivity, High-Resolution Camera, Efficient Performance, Onyx Gray Enhanced Mobile Experience",
        "Price": 662563.6363636364,
        "Rating": "4.0 out of 5 stars",
        "Number of Reviews": "26,159",
        "Image URL": "https://m.media-amazon.com/images/I/61p79A67kPL.__AC_SX300_SY300_QL70_ML2_.jpg",
        "Selected Color": "Onyx Gray",
        "Brand Name": "Xiaomi",
        "Operating System": "Android",
        "RAM Memory Installed": "4 GB",
        "CPU Model": "Snapdragon",
        "CPU Speed": "2.8 GHz",
        "Memory Storage Capacity": "128 GB",
        "Screen Size": "6.67 Inches",
        "Resolution": "1080 x 1920",
        "Refresh Rate": "120 Hz",
        "Model Name": "MZB0DNOEU"
    },
    {
        "Product Name": "Xiaomi Redmi 13C Dual SIM 8GB RAM | 256GB ROM (6.74 Inches) (4G) Midnight Black | 1 year Local warranty",
        "Price": 662563.6363636364,
        "Rating": "3.9 out of 5 stars",
        "Number of Reviews": "603",
        "Image URL": "https://m.media-amazon.com/images/I/51z+jOOKlJL._AC_SY300_SX300_.jpg",
        "Selected Color": "Midnight Black",
        "Brand Name": "Xiaomi",
        "Operating System": "MIUI 14",
        "RAM Memory Installed": "8 GB",
        "CPU Model": "Snapdragon",
        "CPU Speed": "128 GB",
        "Memory Storage Capacity": "6.74 Inches",
        "Screen Size": "1080 x 2400",
        "Resolution": "90 Hz",
        "Refresh Rate": "Redmi 13C",
        "Model Name": "Unlocked for All Carriers"
    },
    {
        "Product Name": "Xiaomi Redmi Note11, 6GB RAM, 128GB ROM - Graphite Gray",
        "Price": 662563.6363636364,
        "Rating": "4.5 out of 5 stars",
        "Number of Reviews": "12,599",
        "Image URL": "https://m.media-amazon.com/images/I/61hj2b6hVJL.__AC_SX300_SY300_QL70_ML2_.jpg",
        "Selected Color": null,
        "Brand Name": "Xiaomi",
        "Operating System": "Android 11.0",
        "RAM Memory Installed": "6 GB",
        "CPU Model": "Snapdragon",
        "CPU Speed": "2.4 GHz",
        "Memory Storage Capacity": "128 GB",
        "Screen Size": "6.43 Inches",
        "Resolution": "1080 x 2400",
        "Refresh Rate": "90 Hz",
        "Model Name": "Redmi Note 11"
    },
    {
        "Product Name": "Xiaomi Redmi 13C (Starshine Green, 8GB RAM, 256GB Storage) | Powered by 4G MediaTek Helio G85 | 90Hz Display | 50MP AI Triple Camera",
        "Price": 695000.0,
        "Rating": "4.1 out of 5 stars",
        "Number of Reviews": "9,820",
        "Image URL": "https://m.media-amazon.com/images/I/71hj88T5aBL.__AC_SX300_SY300_QL70_ML2_.jpg",
        "Selected Color": "Green",
        "Brand Name": "Xiaomi",
        "Operating System": "MIUI 14, Android 13.0",
        "RAM Memory Installed": "8 GB",
        "CPU Model": "MediaTek Helio",
        "CPU Speed": "1 GHz",
        "Memory Storage Capacity": "256 GB",
        "Screen Size": "6.74 Inches",
        "Resolution": "720 x 1600",
        "Refresh Rate": "90 Hz",
        "Model Name": "Redmi 13C"
    },
    {
        "Product Name": "Xiaomi Redmi 10C 4G (Graphite Gray, 4GB RAM, 128 GB Storage) 50mp with 5mp Rare Camera",
        "Price": 662563.6363636364,
        "Rating": "3.9 out of 5 stars",
        "Number of Reviews": "165",
        "Image URL": "https://m.media-amazon.com/images/I/61uD1rfyfoL.__AC_SX300_SY300_QL70_ML2_.jpg",
        "Selected Color": "Graphite Gray",
        "Brand Name": "Xiaomi",
        "Operating System": "MIUI 13",
        "RAM Memory Installed": "4 GB",
        "CPU Model": "Snapdragon",
        "CPU Speed": "2.4 GHz",
        "Memory Storage Capacity": "4 GB",
        "Screen Size": "6.71 Inches",
        "Resolution": "720 x 1600",
        "Refresh Rate": "60 Hz",
        "Model Name": "Redmi 10C"
    },
    {
        "Product Name": "Xiaomi redmi note 11 dual sim amoled dotdisplay star blue 4gb ram 128gb 4g lte, Bluetooth, Wi-Fi, Infrared, USB, NFC",
        "Price": 789900.0,
        "Rating": "4.7 out of 5 stars",
        "Number of Reviews": "3,667",
        "Image URL": "https://m.media-amazon.com/images/I/61sFZSpV3ZL.__AC_SX300_SY300_QL70_ML2_.jpg",
        "Selected Color": "multi",
        "Brand Name": "Xiaomi",
        "Operating System": "Android 11.0",
        "RAM Memory Installed": "128 GB",
        "CPU Model": "Snapdragon",
        "CPU Speed": "2.4 GHz",
        "Memory Storage Capacity": "128 GB",
        "Screen Size": "6.43 Inches",
        "Resolution": "1080 x 2400",
        "Refresh Rate": "90 Hz",
        "Model Name": "Xiaomi Redmi Note 11"
    },
    {
        "Product Name": "Xiaomi Poco F6 5G + 4G LTE 512GB + 12GB Global Version Unlocked 6.67\" 120Hz 50Mp Triple Camera (Tmobile Mint Tello & Global) + (w/Fast Car 51W Bundle) (Black)",
        "Price": 662563.6363636364,
        "Rating": "4.0 out of 5 stars",
        "Number of Reviews": "15",
        "Image URL": "https://m.media-amazon.com/images/I/61INobkIIYL.__AC_SX300_SY300_QL70_ML2_.jpg",
        "Selected Color": null,
        "Brand Name": "Xiaomi",
        "Operating System": "Powered by Xiaomi HyperOS",
        "RAM Memory Installed": "Snapdragon",
        "CPU Model": "2.8 GHz",
        "CPU Speed": "512 GB",
        "Memory Storage Capacity": "6.67 Inches",
        "Screen Size": "2712 x 1220",
        "Resolution": "poco f6",
        "Refresh Rate": "Unlocked for All Carriers",
        "Model Name": "LTE"
    },
    {
        "Product Name": "Xiaomi Redmi Note 13 (Ocean Sunset 8GB RAM, 256 Storage) - Super-clear 108MP triple camera |120Hz FHD+AMOLED display | Immersive viewing with ultra-thin bezels | Secure in-screen fingerprint sensor",
        "Price": 662563.6363636364,
        "Rating": "4.1 out of 5 stars",
        "Number of Reviews": "35",
        "Image URL": "https://m.media-amazon.com/images/I/51-nnAA6T2L.__AC_SX300_SY300_QL70_ML2_.jpg",
        "Selected Color": null,
        "Brand Name": "Xiaomi",
        "Operating System": "MIUI 12",
        "RAM Memory Installed": "8 GB",
        "CPU Model": "Snapdragon",
        "CPU Speed": "256 GB",
        "Memory Storage Capacity": "6.67 Inches",
        "Screen Size": "1080 x 2340",
        "Resolution": "Redmi Note 13",
        "Refresh Rate": "3",
        "Model Name": "4G"
    },
    {
        "Product Name": "Xiaomi Redmi 10A, 4G LTE, 3GB RAM, 64GB ROM - Sky Blue",
        "Price": 509900.0,
        "Rating": "4.3 out of 5 stars",
        "Number of Reviews": "158",
        "Image URL": "https://m.media-amazon.com/images/I/61IXyCCI2AL.__AC_SX300_SY300_QL70_ML2_.jpg",
        "Selected Color": "blue",
        "Brand Name": "Xiaomi",
        "Operating System": "Android 11.0",
        "RAM Memory Installed": "3 GB",
        "CPU Model": "Snapdragon",
        "CPU Speed": "1000 GB",
        "Memory Storage Capacity": "6.53 Inches",
        "Screen Size": "720 x 1600",
        "Resolution": "60 Hz",
        "Refresh Rate": "Redmi 10A",
        "Model Name": "Unlocked for All Carriers"
    },
    {
        "Product Name": "Redmi 13C (Midnight Black 4GB RAM, 128 Storage) -Smooth 6.74\" 90Hz display |50MP AI triple camera |Powerful octa-core processor | Massive 5000 mAh(typ) battery | Supports 18W fast charging UAE VERSION",
        "Price": 585000.0,
        "Rating": "4.1 out of 5 stars",
        "Number of Reviews": "64",
        "Image URL": "https://m.media-amazon.com/images/I/616ATHq0ITL.__AC_SX300_SY300_QL70_ML2_.jpg",
        "Selected Color": null,
        "Brand Name": "Xiaomi",
        "Operating System": "Android 13.0",
        "RAM Memory Installed": "4 GB",
        "CPU Model": "Snapdragon",
        "CPU Speed": "128 GB",
        "Memory Storage Capacity": "6.74 Inches",
        "Screen Size": "90 Hz",
        "Resolution": "Redmi 13C",
        "Refresh Rate": "3",
        "Model Name": "4G"
    },
    {
        "Product Name": "Xiaomi Pad 6, 8GB RAM, 256GB ROM - Mist Blue",
        "Price": 662563.6363636364,
        "Rating": "4.7 out of 5 stars",
        "Number of Reviews": "419",
        "Image URL": "https://m.media-amazon.com/images/I/51HOBCGpgPL.__AC_SX300_SY300_QL70_ML2_.jpg",
        "Selected Color": "Mist Blue",
        "Brand Name": "Xiaomi",
        "Operating System": "VHU4397EU",
        "RAM Memory Installed": "8 GB",
        "CPU Model": "11 Inches",
        "CPU Speed": "1800 x 2880",
        "Memory Storage Capacity": "Android",
        "Screen Size": "Mist Blue",
        "Resolution": "8 GB",
        "Refresh Rate": "Android 13",
        "Model Name": "Fast Charging"
    },
    {
        "Product Name": "Xiaomi Redmi 9A Dual SIM Mobile Phone, 13 MP Camera, 6.53 Inch Touch Screen, 2 GB RAM, 32 GB, 4G LTE - Granite Grey",
        "Price": 479900.0,
        "Rating": "3.8 out of 5 stars",
        "Number of Reviews": "11,190",
        "Image URL": "https://m.media-amazon.com/images/I/41Ty2FvotwS.__AC_SX300_SY300_QL70_ML2_.jpg",
        "Selected Color": "grey",
        "Brand Name": "Xiaomi",
        "Operating System": "Android 10.0",
        "RAM Memory Installed": "2 GB",
        "CPU Model": "Snapdragon",
        "CPU Speed": "2 GHz",
        "Memory Storage Capacity": "32 GB",
        "Screen Size": "6.53 Inches",
        "Resolution": "1280 x 720",
        "Refresh Rate": "60 Hz",
        "Model Name": "Redmi 9A"
    },
    {
        "Product Name": "Xiaomi Redmi 10C Ocean Blue 4GB Ram 128GB Rom",
        "Price": 629900.0,
        "Rating": "3.9 out of 5 stars",
        "Number of Reviews": "39",
        "Image URL": "https://m.media-amazon.com/images/I/51jwhLwKW5L.__AC_SX300_SY300_QL70_ML2_.jpg",
        "Selected Color": "Blue",
        "Brand Name": "Xiaomi",
        "Operating System": "Android 11.0",
        "RAM Memory Installed": "4 GB",
        "CPU Model": "Snapdragon",
        "CPU Speed": "2.4 GHz",
        "Memory Storage Capacity": "128 GB",
        "Screen Size": "6.7 Inches",
        "Resolution": "1080 x 2400",
        "Refresh Rate": "60 Hz",
        "Model Name": "2022"
    },
    {
        "Product Name": "Nokia 106 TA-1564 DS NENA1 Dual SIM 48MB Ram+128MB ROM (1.8 Inches) (2G) - (Charcoal)",
        "Price": 75000.0,
        "Rating": "4.0 out of 5 stars",
        "Number of Reviews": "45",
        "Image URL": "https://m.media-amazon.com/images/I/515X1z3CmML.__AC_SX300_SY300_QL70_ML2_.jpg",
        "Selected Color": null,
        "Brand Name": "Nokia",
        "Operating System": "S30+",
        "RAM Memory Installed": "A10",
        "CPU Model": "0.05 Hz",
        "CPU Speed": "2 GB",
        "Memory Storage Capacity": "1.8 Inches",
        "Screen Size": "1080p",
        "Resolution": "60 Hz",
        "Refresh Rate": "106",
        "Model Name": "Unlocked for All Carriers"
    },
    {
        "Product Name": "Nokia 110 TA-1567 Dual SIM, Feature Phone, 1.8 Inches - Blue",
        "Price": 97500.0,
        "Rating": "3.7 out of 5 stars",
        "Number of Reviews": "25",
        "Image URL": "https://m.media-amazon.com/images/I/61ibfqfxU1L.__AC_SX300_SY300_QL70_ML2_.jpg",
        "Selected Color": "Blue",
        "Brand Name": "Nokia",
        "Operating System": "S30+",
        "RAM Memory Installed": "0.13 GB",
        "CPU Model": "A10",
        "CPU Speed": "2 GB",
        "Memory Storage Capacity": "1.8 Inches",
        "Screen Size": "640 x 480",
        "Resolution": "Nokia 110 Y2023",
        "Refresh Rate": "Unlocked for All Carriers",
        "Model Name": "2G"
    },
    {
        "Product Name": "Nokia g60 5g smartphone, 6.58' hd+ 120hz display, 50mp ai rear camera, 8mp front camera, 6gb ram,128gb storage - grey",
        "Price": 799900.0,
        "Rating": "4.3 out of 5 stars",
        "Number of Reviews": "51",
        "Image URL": "https://m.media-amazon.com/images/I/61kGZOncTpL.__AC_SY300_SX300_QL70_ML2_.jpg",
        "Selected Color": "Grey",
        "Brand Name": "Nokia",
        "Operating System": "Android 12.0",
        "RAM Memory Installed": "6 GB",
        "CPU Model": "Snapdragon",
        "CPU Speed": "2.4 GHz",
        "Memory Storage Capacity": "128 GB",
        "Screen Size": "6.58 Inches",
        "Resolution": "2160 x 1080",
        "Refresh Rate": "120 Hz",
        "Model Name": "Nokia"
    },
    {
        "Product Name": "Nokia c21 plus android smartphone,dual sim,3 gb ram,64 gb memory,6.517\",hd+ lcd with v-notch,android 11 (go edition), fingerprint,face unlock,proximity sensor- dark cyan",
        "Price": 389900.0,
        "Rating": "3.1 out of 5 stars",
        "Number of Reviews": "16",
        "Image URL": "https://m.media-amazon.com/images/I/81AuwSoF9yL.__AC_SY300_SX300_QL70_ML2_.jpg",
        "Selected Color": "Dark Cyan",
        "Brand Name": "Nokia",
        "Operating System": "Android 11.0",
        "RAM Memory Installed": "3 GB",
        "CPU Model": "Snapdragon",
        "CPU Speed": "64 GB",
        "Memory Storage Capacity": "6.52 Inches",
        "Screen Size": "1080 x 2160",
        "Resolution": "144 Hz",
        "Refresh Rate": "Nokia C21+",
        "Model Name": "Unlocked for All Carriers"
    },
    {
        "Product Name": "Nokia 105 TA-1557 Dual Sim 2G Feature Phone, 2 GB Storage- Cyan",
        "Price": 368440.0,
        "Rating": "3.7 out of 5 stars",
        "Number of Reviews": "111",
        "Image URL": "https://m.media-amazon.com/images/I/61skLQO29eL.__AC_SY300_SX300_QL70_ML2_.jpg",
        "Selected Color": "Cyan",
        "Brand Name": "Nokia",
        "Operating System": "S30+",
        "RAM Memory Installed": "A10",
        "CPU Model": "2 GB",
        "CPU Speed": "1.8 Inches",
        "Memory Storage Capacity": "1080p",
        "Screen Size": "70 Hz",
        "Resolution": "105",
        "Refresh Rate": "Unlocked for All Carriers",
        "Model Name": "2G"
    },
    {
        "Product Name": "Nokia g11 plus android smartphone, dual sim, 4gb ram, 64gb memory, 6.5hd+ screen, 5000mah battery, android 12 ready, face unlock, finger print sensor - blue",
        "Price": 479900.0,
        "Rating": "3.9 out of 5 stars",
        "Number of Reviews": "12",
        "Image URL": "https://m.media-amazon.com/images/I/61U-xpxp8TL.__AC_SY300_SX300_QL70_ML2_.jpg",
        "Selected Color": "Blue",
        "Brand Name": "Nokia",
        "Operating System": "Android 12.0",
        "RAM Memory Installed": "4 GB",
        "CPU Model": "Snapdragon",
        "CPU Speed": "64 GB",
        "Memory Storage Capacity": "6.5 Inches",
        "Screen Size": "1080 x 2280",
        "Resolution": "90 Hz",
        "Refresh Rate": "Nokia G11+",
        "Model Name": "Unlocked for All Carriers"
    },
    {
        "Product Name": "HONOR X6b 6GB RAM 128GB, Starry Purple",
        "Price": 610000.0,
        "Rating": "3.4 out of 5 stars",
        "Number of Reviews": "14",
        "Image URL": "https://m.media-amazon.com/images/I/51ZNIVXGt2L.__AC_SX300_SY300_QL70_ML2_.jpg",
        "Selected Color": "Purple",
        "Brand Name": "HONOR",
        "Operating System": "Android T",
        "RAM Memory Installed": "Snapdragon",
        "CPU Model": "6 GB",
        "CPU Speed": "6.56 Inches",
        "Memory Storage Capacity": "1920 x 1080",
        "Screen Size": "120 Hz",
        "Resolution": "X6b",
        "Refresh Rate": "Unlocked for All Carriers",
        "Model Name": "5G"
    },
    {
        "Product Name": "HONOR X7c Dual SIM 8 RAM 256GB Midnight Black 4G - Middle East Version",
        "Price": 899900.0,
        "Rating": "3.0 out of 5 stars",
        "Number of Reviews": "25",
        "Image URL": "https://m.media-amazon.com/images/I/81jhIJ6Vt0L._AC_SY300_SX300_.jpg",
        "Selected Color": "Midnight Black",
        "Brand Name": "HONOR",
        "Operating System": "Android 14",
        "RAM Memory Installed": "Snapdragon",
        "CPU Model": "256 GB",
        "CPU Speed": "6.8 Inches",
        "Memory Storage Capacity": "1512x720 pixels",
        "Screen Size": "120 Hz",
        "Resolution": "5109BKDN",
        "Refresh Rate": "Unlocked for All Carriers",
        "Model Name": "4G"
    },
    {
        "Product Name": "HONOR X9c 5G 12GB RAM 256GB Dual SIM Sunrise Orange With Free Gifts",
        "Price": 2188800.0,
        "Rating": "3.7 out of 5 stars",
        "Number of Reviews": "25",
        "Image URL": "https://m.media-amazon.com/images/I/81EKbLaml0L.__AC_SX300_SY300_QL70_ML2_.jpg",
        "Selected Color": "Sunrise Orange",
        "Brand Name": "HONOR",
        "Operating System": "Android 14",
        "RAM Memory Installed": "12 GB",
        "CPU Model": "Qualcomm Snapdragon S4 MSM8270",
        "CPU Speed": "1 GHz",
        "Memory Storage Capacity": "256 GB",
        "Screen Size": "6.78 Inches",
        "Resolution": "120 Hz",
        "Refresh Rate": "Unlocked for All Carriers",
        "Model Name": "5G"
    },
    {
        "Product Name": "HONOR X9b Dual SIM 5G 12GB RAM 256GB ROM - Sunrise Orange - Local Warranty",
        "Price": 1495500.0,
        "Rating": null,
        "Number of Reviews": "No featured offers available",
        "Image URL": "https://m.media-amazon.com/images/I/81FmX+ooJQL._AC_SY300_SX300_.jpg",
        "Selected Color": null,
        "Brand Name": "HONOR",
        "Operating System": "Android",
        "RAM Memory Installed": "12 GB",
        "CPU Model": "256 GB",
        "CPU Speed": "6.78 Inches",
        "Memory Storage Capacity": "120 hertz",
        "Screen Size": "Honor X9b",
        "Resolution": "Unlocked",
        "Refresh Rate": "5G",
        "Model Name": "Sunrise Orange"
    },
    {
        "Product Name": "HONOR X6b 6GB+256GB Forest Green",
        "Price": 1495500.0,
        "Rating": null,
        "Number of Reviews": "No featured offers available",
        "Image URL": "https://m.media-amazon.com/images/I/51P4zFM7c6L.__AC_SX300_SY300_QL70_ML2_.jpg",
        "Selected Color": null,
        "Brand Name": "HONOR",
        "Operating System": "Android T",
        "RAM Memory Installed": "Snapdragon",
        "CPU Model": "6 GB",
        "CPU Speed": "6.56 Inches",
        "Memory Storage Capacity": "120 Hz",
        "Screen Size": "Judy-L52F",
        "Resolution": "Unlocked for All Carriers",
        "Refresh Rate": "Sunrise Orange",
        "Model Name": "Wi-Fi"
    },
    {
        "Product Name": "HONOR X6b 6GB+256GB Starry Purple",
        "Price": 1495500.0,
        "Rating": null,
        "Number of Reviews": "No featured offers available",
        "Image URL": "https://m.media-amazon.com/images/I/51oE8E3OAzL.__AC_SX300_SY300_QL70_ML2_.jpg",
        "Selected Color": null,
        "Brand Name": "HONOR",
        "Operating System": "Android T",
        "RAM Memory Installed": "Snapdragon",
        "CPU Model": "6 GB",
        "CPU Speed": "6.56 Inches",
        "Memory Storage Capacity": "3840 x 2160",
        "Screen Size": "120 Hz",
        "Resolution": "Judy-L52F",
        "Refresh Rate": "Unlocked for All Carriers",
        "Model Name": "5G"
    },
    {
        "Product Name": "HONOR X9b 5G Sunrise Orange, 12GB RAM + 256GB ROM, Dual Sim, 120Hz Curved AMOLED Display, 5800 mAh Battery, 108MP Triple Camera, 4nm Snapdragon 6 Gen 1 Chipset, Android 13 +Exclusive Gifts",
        "Price": 1495500.0,
        "Rating": "3.6 out of 5 stars",
        "Number of Reviews": "132",
        "Image URL": "https://m.media-amazon.com/images/I/71xlPKVjN4L.__AC_SX300_SY300_QL70_ML2_.jpg",
        "Selected Color": null,
        "Brand Name": "HONOR",
        "Operating System": "Android 13.0",
        "RAM Memory Installed": "12 GB",
        "CPU Model": "Snapdragon",
        "CPU Speed": "12 GB",
        "Memory Storage Capacity": "5.7 Inches",
        "Screen Size": "120 Hz",
        "Resolution": "Honor X9b",
        "Refresh Rate": "Unlocked for All Carriers",
        "Model Name": "5G"
    },
    {
        "Product Name": "HONOR 200 5G 12GB RAM + 256GB Dual SIM Moonlight White - Middle East Version",
        "Price": 1495500.0,
        "Rating": "4.5 out of 5 stars",
        "Number of Reviews": "2",
        "Image URL": "https://m.media-amazon.com/images/I/61nE1hMBmQL.__AC_SX300_SY300_QL70_ML2_.jpg",
        "Selected Color": null,
        "Brand Name": "HONOR",
        "Operating System": "Android 14",
        "RAM Memory Installed": "12 GB",
        "CPU Model": "Snapdragon",
        "CPU Speed": "256 GB",
        "Memory Storage Capacity": "6.7 Inches",
        "Screen Size": "120 Hz",
        "Resolution": "Unlocked for All Carriers",
        "Refresh Rate": "5G",
        "Model Name": "Wi-Fi"
    },
    {
        "Product Name": "HONOR 200 Pro 5G 12GB RAM + 512GB Dual SIM Ocean Cyan - Middle East Version",
        "Price": 3288800.0,
        "Rating": null,
        "Number of Reviews": "Only 1 left in stock - order soon.",
        "Image URL": "https://m.media-amazon.com/images/I/61pRiBZxDrL.__AC_SX300_SY300_QL70_ML2_.jpg",
        "Selected Color": null,
        "Brand Name": "HONOR",
        "Operating System": "Android 14",
        "RAM Memory Installed": "12 GB",
        "CPU Model": "Snapdragon",
        "CPU Speed": "512 GB",
        "Memory Storage Capacity": "6.78 Inches",
        "Screen Size": "120 Hz",
        "Resolution": "HONOR 200 Pro",
        "Refresh Rate": "Unlocked for All Carriers",
        "Model Name": "5G"
    },
    {
        "Product Name": "HONOR X5b 4GB RAM 64GB Internal Storage 5200mAH - Midnight Black",
        "Price": 490000.0,
        "Rating": null,
        "Number of Reviews": null,
        "Image URL": "https://m.media-amazon.com/images/I/812N9FNkncL.__AC_SX300_SY300_QL70_ML2_.jpg",
        "Selected Color": null,
        "Brand Name": "HONOR",
        "Operating System": "Android 14",
        "RAM Memory Installed": "64 GB",
        "CPU Model": "6.6 Inches",
        "CPU Speed": "x5b",
        "Memory Storage Capacity": "Unlocked for All Carriers",
        "Screen Size": "4G",
        "Resolution": "Midnight Black",
        "Refresh Rate": "USB Type C",
        "Model Name": "Slate"
    },
    {
        "Product Name": "Realme 12 5G 8-256 Green",
        "Price": 777700.0,
        "Rating": "2.2 out of 5 stars",
        "Number of Reviews": "10",
        "Image URL": "https://m.media-amazon.com/images/I/81dA4WginXL.__AC_SX300_SY300_QL70_ML2_.jpg",
        "Selected Color": null,
        "Brand Name": "realme",
        "Operating System": "Android 14, Realme UI 5.0",
        "RAM Memory Installed": "8 GB",
        "CPU Model": "Others",
        "CPU Speed": "256 GB",
        "Memory Storage Capacity": "6.75 Inches",
        "Screen Size": "1080 x 2400",
        "Resolution": "Realme 12",
        "Refresh Rate": "Unlocked for All Carriers",
        "Model Name": "Wi-Fi"
    },
    {
        "Product Name": "realme c65 Smartphone 6+128 GB, 50MP AI Camera, 6.67 Inch Eye Comfort Display with 90Hz Refresh Rate, 45W Fast Charge, 5000mAh Massive Battery, NFC Supported, Starlight Gold",
        "Price": 777700.0,
        "Rating": "3.6 out of 5 stars",
        "Number of Reviews": "8",
        "Image URL": "https://m.media-amazon.com/images/I/71nva4btzuL.__AC_SX300_SY300_QL70_ML2_.jpg",
        "Selected Color": null,
        "Brand Name": "realme",
        "Operating System": "Android",
        "RAM Memory Installed": "Snapdragon",
        "CPU Model": "128 GB",
        "CPU Speed": "6.4 Inches",
        "Memory Storage Capacity": "1080 x 2400",
        "Screen Size": "realme C65",
        "Resolution": "Unlocked for All Carriers",
        "Refresh Rate": "NFC",
        "Model Name": "NFC"
    },
    {
        "Product Name": "realme c65 Smartphone 8+256 GB, 50MP AI Camera, 6.67 Inch Eye Comfort Display with 90Hz Refresh Rate, 45 W Fast Charge, 5000 mAh Solid Battery, NFC Supported, Starlight Gold",
        "Price": 777700.0,
        "Rating": "3.8 out of 5 stars",
        "Number of Reviews": "57",
        "Image URL": "https://m.media-amazon.com/images/I/71nva4btzuL.__AC_SX300_SY300_QL70_ML2_.jpg",
        "Selected Color": null,
        "Brand Name": "realme",
        "Operating System": "Android",
        "RAM Memory Installed": "Snapdragon",
        "CPU Model": "256 GB",
        "CPU Speed": "6.4 Inches",
        "Memory Storage Capacity": "1080 x 2400",
        "Screen Size": "90 Hz",
        "Resolution": "realme C65",
        "Refresh Rate": "Unlocked for All Carriers",
        "Model Name": "NFC"
    },
    {
        "Product Name": "realme 12 Pro 5G Dual SIM 12GB RAM 512GB - Middle East Version (Navigator Beige)",
        "Price": 777700.0,
        "Rating": "4.5 out of 5 stars",
        "Number of Reviews": "8",
        "Image URL": "https://m.media-amazon.com/images/I/81gb8QD+WOL._AC_SY300_SX300_.jpg",
        "Selected Color": "Navigator Beige",
        "Brand Name": "realme",
        "Operating System": "Android 12.0",
        "RAM Memory Installed": "12 GB",
        "CPU Model": "Snapdragon",
        "CPU Speed": "2.4 GHz",
        "Memory Storage Capacity": "12 GB",
        "Screen Size": "6.7 Inches",
        "Resolution": "1080 x 2400",
        "Refresh Rate": "120 Hz",
        "Model Name": "realme 12"
    },
    {
        "Product Name": "Realme C65 4G, 8GB Ram, 256GB Storage, Dual SIM Slot, 50MP AI Camera, 45 W Fast Charge, 5000 mAh Massive Battery - Starlight Black",
        "Price": 777700.0,
        "Rating": "4.0 out of 5 stars",
        "Number of Reviews": "59",
        "Image URL": "https://m.media-amazon.com/images/I/71jiC-le4hL.__AC_SX300_SY300_QL70_ML2_.jpg",
        "Selected Color": null,
        "Brand Name": "realme",
        "Operating System": "Android",
        "RAM Memory Installed": "8 GB",
        "CPU Model": "Snapdragon",
        "CPU Speed": "256 GB",
        "Memory Storage Capacity": "6.4 Inches",
        "Screen Size": "1080 x 2400",
        "Resolution": "realme C65",
        "Refresh Rate": "Unlocked for All Carriers",
        "Model Name": "NFC"
    },
    {
        "Product Name": "realme C67 Dual-SIM 128GB ROM + 6GB RAM 4G (Sunny Oasis) - International Version",
        "Price": 777700.0,
        "Rating": "3.5 out of 5 stars",
        "Number of Reviews": "6",
        "Image URL": "https://m.media-amazon.com/images/I/71HOnHVxwyL.__AC_SX300_SY300_QL70_ML2_.jpg",
        "Selected Color": null,
        "Brand Name": "realme",
        "Operating System": "Android 14",
        "RAM Memory Installed": "6 GB",
        "CPU Model": "Snapdragon",
        "CPU Speed": "2.4 GHz",
        "Memory Storage Capacity": "128 GB",
        "Screen Size": "6.72 Inches",
        "Resolution": "1080 x 2400",
        "Refresh Rate": "120 Hz",
        "Model Name": "Realme C67 4G"
    },
    {
        "Product Name": "Realme C65 4G 6GB RAM + 128GB \u2013 Gold",
        "Price": 777700.0,
        "Rating": null,
        "Number of Reviews": "Only 1 left in stock - order soon.",
        "Image URL": "https://m.media-amazon.com/images/I/51mJthLzsOL.__AC_SX300_SY300_QL70_ML2_.jpg",
        "Selected Color": null,
        "Brand Name": "realme",
        "Operating System": "6 GB",
        "RAM Memory Installed": "Snapdragon",
        "CPU Model": "128 GB",
        "CPU Speed": "6.5 Inches",
        "Memory Storage Capacity": "1080 x 2400",
        "Screen Size": "Realme C65",
        "Resolution": "4G",
        "Refresh Rate": "Bluetooth, Wi-Fi",
        "Model Name": "Gold"
    },
    {
        "Product Name": "realme C21Y Dual Sim 64GB 4GB RAM, 4G Lte Phone 6.5in, Black)",
        "Price": 777700.0,
        "Rating": "4.4 out of 5 stars",
        "Number of Reviews": "24",
        "Image URL": "https://m.media-amazon.com/images/I/61jAfCRJq2L.__AC_SX300_SY300_QL70_ML2_.jpg",
        "Selected Color": null,
        "Brand Name": "realme",
        "Operating System": "Android 10.0",
        "RAM Memory Installed": "4 GB",
        "CPU Model": "Snapdragon",
        "CPU Speed": "4 GB",
        "Memory Storage Capacity": "6.5 Inches",
        "Screen Size": "720 x 1600",
        "Resolution": "60 Hz",
        "Refresh Rate": "Unlocked for All Carriers",
        "Model Name": "4G"
    },
    {
        "Product Name": "realme 7i 128 GB, 8GB RAM 4G Lte Dual Sim Phone (Polar Blue)",
        "Price": 777700.0,
        "Rating": "5.0 out of 5 stars",
        "Number of Reviews": "1",
        "Image URL": "https://m.media-amazon.com/images/I/51y0vE4L85L.__AC_SX300_SY300_QL70_ML2_.jpg",
        "Selected Color": "Blue",
        "Brand Name": "realme",
        "Operating System": "Android 10.0",
        "RAM Memory Installed": "8 GB",
        "CPU Model": "Snapdragon",
        "CPU Speed": "2.84 GHz",
        "Memory Storage Capacity": "128 GB",
        "Screen Size": "6.5 Inches",
        "Resolution": "720 x 1600",
        "Refresh Rate": "90 Hz",
        "Model Name": "realme 7i"
    },
    {
        "Product Name": "Oppo Reno 12F 5G Mobile Phone, Dual SIM, 12GB Ram, 256GB - Olive Green",
        "Price": null,
        "Rating": "3.6 out of 5 stars",
        "Number of Reviews": "21",
        "Image URL": "https://m.media-amazon.com/images/I/61sIzvW9g6L.__AC_SX300_SY300_QL70_ML2_.jpg",
        "Selected Color": null,
        "Brand Name": "OPPO",
        "Operating System": "ColorOS 14.0",
        "RAM Memory Installed": "12 GB",
        "CPU Model": "2.2E+3 MHz",
        "CPU Speed": "12 GB",
        "Memory Storage Capacity": "6.67 Inches",
        "Screen Size": "1080 x 2400",
        "Resolution": "Oppo Reno 12F",
        "Refresh Rate": "Unlocked",
        "Model Name": "5G"
    },
    {
        "Product Name": "OPPO A3 128GB 6GB Sparkle Black AE",
        "Price": null,
        "Rating": "2.9 out of 5 stars",
        "Number of Reviews": "2",
        "Image URL": "https://m.media-amazon.com/images/I/71vVYQwH1yL.__AC_SX300_SY300_QL70_ML2_.jpg",
        "Selected Color": null,
        "Brand Name": "OPPO",
        "Operating System": "Android",
        "RAM Memory Installed": "6 GB",
        "CPU Model": "Snapdragon",
        "CPU Speed": "128 GB",
        "Memory Storage Capacity": "6.67 Inches",
        "Screen Size": "OPPO A3",
        "Resolution": "Unlocked for All Carriers",
        "Refresh Rate": "4G",
        "Model Name": "Wi-Fi"
    },
    {
        "Product Name": "OPPO A3 128GB 6GB Starlight White AE",
        "Price": null,
        "Rating": null,
        "Number of Reviews": "No featured offers available",
        "Image URL": "https://m.media-amazon.com/images/I/71SmMpDpSPL._AC_SY300_SX300_.jpg",
        "Selected Color": null,
        "Brand Name": "OPPO",
        "Operating System": "android",
        "RAM Memory Installed": "6 GB",
        "CPU Model": "Snapdragon",
        "CPU Speed": "128 GB",
        "Memory Storage Capacity": "6.67 Inches",
        "Screen Size": "Unlocked for All Carriers",
        "Resolution": "White",
        "Refresh Rate": "LTE",
        "Model Name": "2024"
    },
    {
        "Product Name": "OPPO A60 256GB 8GB, Android Smartphone Midnight Purple, 14.0 Colour OS Version, 45W Super VOOC Flash Charge",
        "Price": null,
        "Rating": "3.9 out of 5 stars",
        "Number of Reviews": "24",
        "Image URL": "https://m.media-amazon.com/images/I/71BYdZpMipL._AC_SY300_SX300_.jpg",
        "Selected Color": null,
        "Brand Name": "OPPO",
        "Operating System": "Android",
        "RAM Memory Installed": "8 GB",
        "CPU Model": "Snapdragon",
        "CPU Speed": "8 GB",
        "Memory Storage Capacity": "6.7 Inches",
        "Screen Size": "OPPO A60",
        "Resolution": "Unlocked for All Carriers",
        "Refresh Rate": "Bluetooth, Wi-Fi, USB",
        "Model Name": "Midnight Purple"
    },
    {
        "Product Name": "Oppo Reno 12F 4G, 8GB Ram Snapdragon 685, 256GB Storage, 5000mAh & Dual SIM Slot - Matte Grey",
        "Price": null,
        "Rating": "3.9 out of 5 stars",
        "Number of Reviews": "6",
        "Image URL": "https://m.media-amazon.com/images/I/61UI7GS5NaL.__AC_SX300_SY300_QL70_ML2_.jpg",
        "Selected Color": null,
        "Brand Name": "OPPO",
        "Operating System": "8 GB",
        "RAM Memory Installed": "Snapdragon",
        "CPU Model": "256 GB",
        "CPU Speed": "6.55 Inches",
        "Memory Storage Capacity": "1080 x 2340",
        "Screen Size": "Oppo Reno 12F 4G",
        "Resolution": "4G",
        "Refresh Rate": "Bluetooth, Wi-Fi",
        "Model Name": "Matte Grey"
    },
    {
        "Product Name": "OPPO A3x, 4GB Ram, 128GB Storage - Nebula Red",
        "Price": null,
        "Rating": "1.0 out of 5 stars",
        "Number of Reviews": "1",
        "Image URL": "https://m.media-amazon.com/images/I/71UuLg6H8uL._AC_SY300_SX300_.jpg",
        "Selected Color": null,
        "Brand Name": "OPPO",
        "Operating System": "Android 14",
        "RAM Memory Installed": "4 GB",
        "CPU Model": "Snapdragon",
        "CPU Speed": "128 GB",
        "Memory Storage Capacity": "6.67 Inches",
        "Screen Size": "OPPO A3x 128GB 4GB Nebula Red",
        "Resolution": "Unlocked for All Carriers",
        "Refresh Rate": "Nebula Red",
        "Model Name": "LTE"
    },
    {
        "Product Name": "OPPO A3x 128GB 4GB Ocean Blue AE",
        "Price": null,
        "Rating": "3.6 out of 5 stars",
        "Number of Reviews": "3",
        "Image URL": "https://m.media-amazon.com/images/I/71+GrIzUpvL._AC_SY300_SX300_.jpg",
        "Selected Color": null,
        "Brand Name": "OPPO",
        "Operating System": "android",
        "RAM Memory Installed": "Snapdragon",
        "CPU Model": "128 GB",
        "CPU Speed": "6.67 Inches",
        "Memory Storage Capacity": "OPPO A3x 128GB 4GB Ocean Blue",
        "Screen Size": "Unlocked for All Carriers",
        "Resolution": "Ocean Blue",
        "Refresh Rate": "LTE",
        "Model Name": "2024"
    }
]